scopeprof.py
scopeprof-0.1.0.dist-info/METADATA
scopeprof-0.1.0.dist-info/WHEEL
scopeprof-0.1.0.dist-info/top_level.txt
scopeprof-0.1.0.dist-info/RECORD
