Metadata-Version: 2.4
Name: scopeprof
Version: 0.1.0
Summary: Simple function/block profiler with HTTP export
Author: 490103404@qq.com
Requires-Python: >=3.6
Dynamic: author
Dynamic: requires-python
Dynamic: summary
